setup.py
docker_introspection.egg-info/PKG-INFO
docker_introspection.egg-info/SOURCES.txt
docker_introspection.egg-info/dependency_links.txt
docker_introspection.egg-info/entry_points.txt
docker_introspection.egg-info/requires.txt
docker_introspection.egg-info/top_level.txt
src/docker_introspection/__init__.py
src/docker_introspection/docker_introspection.py