Metadata-Version: 1.0
Name: docker-introspection
Version: 0.1.0
Summary: An HTTP read only API for container introspection
Home-page: UNKNOWN
Author: Avishai Ish-Shalom
Author-email: UNKNOWN
License: UNKNOWN
Platform: UNKNOWN
